ds_arpes_plugin/__init__.py
ds_arpes_plugin/ds_arpes_plugin.py
ds_arpes_plugin-0.0.2.dist-info/LICENSE
ds_arpes_plugin-0.0.2.dist-info/METADATA
ds_arpes_plugin-0.0.2.dist-info/WHEEL
ds_arpes_plugin-0.0.2.dist-info/top_level.txt
ds_arpes_plugin-0.0.2.dist-info/RECORD
